LICENSE
MANIFEST.in
README.md
setup.py
virtualtime/__init__.py
virtualtime/test_virtualtime.py
virtualtime.egg-info/PKG-INFO
virtualtime.egg-info/SOURCES.txt
virtualtime.egg-info/dependency_links.txt
virtualtime.egg-info/pbr.json
virtualtime.egg-info/requires.txt
virtualtime.egg-info/top_level.txt
virtualtime/datetime_tz/__init__.py
virtualtime/datetime_tz/test_datetime_tz.py